json_to_files/__init__.py
json_to_files/__main__.py
json_to_files/cli.py
json_to_files-0.1.dist-info/LICENSE
json_to_files-0.1.dist-info/METADATA
json_to_files-0.1.dist-info/WHEEL
json_to_files-0.1.dist-info/entry_points.txt
json_to_files-0.1.dist-info/top_level.txt
json_to_files-0.1.dist-info/RECORD
