Metadata-Version: 2.1
Name: json-to-files
Version: 0.1
Summary: Create separate files on disk based on a JSON object
Home-page: https://github.com/simonw/json-to-files
Author: Simon Willison
License: Apache License, Version 2.0
Project-URL: Issues, https://github.com/simonw/json-to-files/issues
Project-URL: CI, https://github.com/simonw/json-to-files/actions
Project-URL: Changelog, https://github.com/simonw/json-to-files/releases
Requires-Python: >=3.7
License-File: LICENSE
Requires-Dist: click
Provides-Extra: test
Requires-Dist: pytest ; extra == 'test'
